credentialdigger/__init__.py
credentialdigger/__main__.py
credentialdigger/client.py
credentialdigger/client_postgres.py
credentialdigger/client_sqlite.py
credentialdigger/snippet_similarity.py
credentialdigger/cli/__init__.py
credentialdigger/cli/add_rules.py
credentialdigger/cli/cli.py
credentialdigger/cli/get_discoveries.py
credentialdigger/cli/hook.py
credentialdigger/cli/scan.py
credentialdigger/cli/scan_path.py
credentialdigger/cli/scan_pr.py
credentialdigger/cli/scan_snapshot.py
credentialdigger/cli/scan_user.py
credentialdigger/cli/scan_wiki.py
credentialdigger/models/__init__.py
credentialdigger/models/base_model.py
credentialdigger/models/model_manager.py
credentialdigger/models/password_model.py
credentialdigger/models/path_model.py
credentialdigger/scanners/__init__.py
credentialdigger/scanners/base_scanner.py
credentialdigger/scanners/file_scanner.py
credentialdigger/scanners/git_file_scanner.py
credentialdigger/scanners/git_pr_scanner.py
credentialdigger/scanners/git_scanner.py
credentialdigger-4.15.0.dist-info/licenses/LICENSE
credentialdigger-4.15.0.dist-info/METADATA
credentialdigger-4.15.0.dist-info/WHEEL
credentialdigger-4.15.0.dist-info/entry_points.txt
credentialdigger-4.15.0.dist-info/top_level.txt
credentialdigger-4.15.0.dist-info/RECORD
