Metadata-Version: 2.4
Name: credentialdigger
Version: 4.15.0
Summary: Credential Digger
Author: SAP SE
Maintainer-email: Marco Rosa <marco.rosa@sap.com>, Slim Trabelsi <slim.trabelsi@sap.com>
License:                                  Apache License
Project-URL: Homepage, https://github.com/sap/credential-digger
Project-URL: Documentation, https://github.com/SAP/credential-digger/wiki
Project-URL: Repository, https://github.com/sap/credential-digger.git
Project-URL: Issues, https://github.com/SAP/credential-digger/issues
Classifier: Programming Language :: Python :: 3
Classifier: Programming Language :: Python :: 3.9
Classifier: Programming Language :: Python :: 3.10
Classifier: Programming Language :: Python :: 3.11
Classifier: Programming Language :: Python :: 3.12
Classifier: Operating System :: OS Independent
Classifier: Topic :: Security
Requires-Python: <3.13,>3.8
License-File: LICENSE
Requires-Dist: Flask
Requires-Dist: flask_jwt_extended
Requires-Dist: GitPython
Requires-Dist: hyperscan==0.7.8; python_version == "3.9"
Requires-Dist: hyperscan==0.7.13; python_version != "3.9"
Requires-Dist: numpy
Requires-Dist: pandas
Requires-Dist: psycopg2-binary
Requires-Dist: PyGithub
Requires-Dist: python-dotenv
Requires-Dist: pyyaml
Requires-Dist: rich~=14.1
Requires-Dist: srsly>=2.4.0
Requires-Dist: tensorflow==2.19.0
Requires-Dist: tensorflow-text==2.19.0
Requires-Dist: tf-models-official
Requires-Dist: transformers
Dynamic: license-file
